genagg/AggGNN.py
genagg/GenAgg.py
genagg/GenAggSparse.py
genagg/MLP.py
genagg/__init__.py
genagg-0.0.3.dist-info/METADATA
genagg-0.0.3.dist-info/WHEEL
genagg-0.0.3.dist-info/top_level.txt
genagg-0.0.3.dist-info/RECORD
